<?xml version="1.0" encoding="UTF-8" ?><mediawiki xmlns="http://www.mediawiki.org/xml/export-0.4/" xmlns:xsi="http://www.w3.org/2001/XMLSchema-instance" xsi:schemaLocation="http://www.mediawiki.org/xml/export-0.4/ http://www.mediawiki.org/xml/export-0.4.xsd" version="0.4" xml:lang="en"><page>
    <title>NCS Lab 2016</title>
    <revision><timestamp>2016-08-17T08:58:20Z</timestamp><text xml:space="preserve">{{Event
|Acronym=NCS Lab 2016
|Title=NCS Lab  2016 : Narrative, Cognition &amp; Science Lab
|Type=Conference
|Field=cognitive science, narrative, science, literature
|Start date=2016-10-21T00:00:00
|End date=2016-10-23T23:59:59
|City=Erlangen
|Country=Germany
|Homepage=elinas.fau.de/
|Abstract deadline = 
|Notification = 2016-09-15T00:00:00
|Submission deadline= 2016-08-31T00:00:00
}}</text>
    </revision>
  </page>
<page>
    <title>SOFEA 2016</title>
    <revision><timestamp>2016-08-17T08:58:20Z</timestamp><text xml:space="preserve">{{Event
|Acronym=SOFEA 2016
|Title=SOFEA  2016 :  2nd International Conference on Software Engineering and Applications
|Type=Conference
|Field=software engineering, software, engineering, applications
|Start date=2016-08-27T00:00:00
|End date=2016-08-28T23:59:59
|City=Dubai
|Country=UAE
|Homepage=csen2016.org/sofea/index.html
|Abstract deadline = 
|Notification = 2016-08-20T00:00:00
|Submission deadline= 2016-08-06T00:00:00
}}</text>
    </revision>
  </page>
<page>
    <title>ITIC 2017</title>
    <revision><timestamp>2016-08-17T08:58:20Z</timestamp><text xml:space="preserve">{{Event
|Acronym=ITIC 2017
|Title=ITIC  2017 : 11th International Conference on Translation and Interpreting: Justice and minorized languages under a postmonolingual order
|Type=Conference
|Field=translation, interpreting, law, languages
|Start date=2017-05-10T00:00:00
|End date=2017-05-12T23:59:59
|City=Castelló de la Plana
|Country=Spain
|Homepage=blogs.uji.es/itic11/
|Abstract deadline = 
|Notification = 2016-10-15T00:00:00
|Submission deadline= 2016-09-05T00:00:00
}}</text>
    </revision>
  </page>
<page>
    <title>FPGA4GPC 2017</title>
    <revision><timestamp>2016-08-17T08:58:20Z</timestamp><text xml:space="preserve">{{Event
|Acronym=FPGA4GPC 2017
|Title=FPGA4GPC  2017 : International Conference on FPGA Reconfiguration for General-Purpose Computing 2017
|Type=Conference
|Field=computer science, FPGA, reconfiguration, operating system
|Start date=2017-05-09T00:00:00
|End date=2017-05-10T23:59:59
|City=Hamburg
|Country=Germany
|Homepage=www.fpga4gpc.org
|Abstract deadline = 
|Notification = 2017-02-28T00:00:00
|Submission deadline= 2017-01-11T00:00:00
}}</text>
    </revision>
  </page>
<page>
    <title>AES 2016</title>
    <revision><timestamp>2016-08-17T08:58:20Z</timestamp><text xml:space="preserve">{{Event
|Acronym=AES 2016
|Title=AES  2016 : Asian Education Symposium
|Type=Conference
|Field=education, pedagogy, teaching methodologies and ass, educational foundations
|Start date=2016-11-22T00:00:00
|End date=2016-11-23T23:59:59
|City=Bandung
|Country=INDONESIA
|Homepage=aes.conference.upi.edu/
|Abstract deadline = 2016-07-30T00:00:00
|Notification = 2016-10-05T00:00:00
|Submission deadline= 2016-09-30T00:00:00
}}</text>
    </revision>
  </page>
<page>
    <title>ETAEc 2016</title>
    <revision><timestamp>2016-08-17T08:58:20Z</timestamp><text xml:space="preserve">{{Event
|Acronym=ETAEc 2016
|Title=ETAEc  2016 : 2nd International Conference on Emerging Trends and Approaches, 12th-13th  November 2016
|Type=Conference
|Field=economy, management, marketing, business informatics
|Start date=2016-11-12T00:00:00
|End date=2016-11-13T23:59:59
|City=University of Pitesti
|Country=Romania
|Homepage=www.etaec.eu
|Abstract deadline = 2016-09-01T00:00:00
|Notification = 2016-10-10T00:00:00
|Submission deadline= 2016-09-30T00:00:00
}}</text>
    </revision>
  </page>
<page>
    <title>HPCAC 2016</title>
    <revision><timestamp>2016-08-17T08:58:20Z</timestamp><text xml:space="preserve">{{Event
|Acronym=HPCAC 2016
|Title=HPCAC  2016 : 5th Annual Spain Conference 2016
|Type=Conference
|Field=high performance computing, machine learning, data analytics, big data
|Start date=2016-09-21T00:00:00
|End date=2016-09-21T23:59:59
|City=Leon Spain
|Country=
|Homepage=hpcadvisorycouncil.com/events/2016/spain-conference/
|Abstract deadline = 
|Notification = 2016-08-01T00:00:00
|Submission deadline= 2016-07-01T00:00:00
}}</text>
    </revision>
  </page>
<page>
    <title>IEEE-CEMAG-SI-VRAR 2017</title>
    <revision><timestamp>2016-08-17T08:58:20Z</timestamp><text xml:space="preserve">{{Event
|Acronym=IEEE-CEMAG-SI-VRAR 2017
|Title=IEEE-CEMAG-SI-VRAR  2017 : IEEE CE Magazine - Special Issue on Advanced Interaction and Virtual-Augmented Reality
|Type=Conference
|Field=augmented reality, virtual reality, human-machine interaction
|Start date=
|End date=
|City=
|Country=
|Homepage=specialvr.ieee-cesoc.org/
|Abstract deadline = 
|Notification = 
|Submission deadline= 2016-12-15T00:00:00
}}</text>
    </revision>
  </page>
<page>
    <title>OBIS 2016</title>
    <revision><timestamp>2016-08-17T08:58:20Z</timestamp><text xml:space="preserve">{{Event
|Acronym=OBIS 2016
|Title=OBIS  2016 : 1st Workshop on Open Business Intelligence Systems (OBIS 2016)  Collocated with:  SITIS 2016 - The 12th International Conference on SIGNAL IMAGE TECHNOLOGY &amp; INTERNET BASED SYSTEMS
|Type=Conference
|Field=computer sciences, business intelligence, decision-making, big data
|Start date=2016-11-28T00:00:00
|End date=2016-12-01T23:59:59
|City=Naples
|Country=Italy
|Homepage=sitis-conf.org/en/obis-16.php
|Abstract deadline = 
|Notification = 2016-10-09T00:00:00
|Submission deadline= 2016-09-11T00:00:00
}}</text>
    </revision>
  </page>
<page>
    <title>Symbolism 2016</title>
    <revision><timestamp>2016-08-17T08:58:20Z</timestamp><text xml:space="preserve">{{Event
|Acronym=Symbolism 2016
|Title=Symbolism  2016 : International Seminar on “Symbolism in Indian Art, Archaeology and Literature”
|Type=Conference
|Field=symbolism, literature, archeology, anthropology
|Start date=2016-12-01T00:00:00
|End date=2016-12-03T23:59:59
|City=Pune
|Country=
|Homepage=dcpune.ac.in/first-circular-international-seminar.php
|Abstract deadline = 2016-10-15T00:00:00
|Notification = 
|Submission deadline= 2016-09-15T00:00:00
}}</text>
    </revision>
  </page>
</mediawiki>